ProxyManager/__init__.py
ProxyManager/_nbdev.py
ProxyManager/core.py
ProxyManager/free_proxies.py
ProxyManager-0.0.6.dist-info/LICENSE
ProxyManager-0.0.6.dist-info/METADATA
ProxyManager-0.0.6.dist-info/WHEEL
ProxyManager-0.0.6.dist-info/entry_points.txt
ProxyManager-0.0.6.dist-info/top_level.txt
ProxyManager-0.0.6.dist-info/RECORD
